kronoslabs/__init__.py
kronoslabs/client.py
kronoslabs/exceptions.py
kronoslabs/models.py
kronoslabs-1.1.2.dist-info/licenses/LICENSE
kronoslabs-1.1.2.dist-info/METADATA
kronoslabs-1.1.2.dist-info/WHEEL
kronoslabs-1.1.2.dist-info/top_level.txt
kronoslabs-1.1.2.dist-info/RECORD
